{
    "os": "Linux-5.15.0-88-generic-x86_64-with-glibc2.29",
    "python": "3.8.10",
    "heartbeatAt": "2024-07-03T19:12:50.448350",
    "startedAt": "2024-07-03T19:12:50.216603",
    "docker": null,
    "cuda": null,
    "args": [
        "--config",
        "/home/tony/APS360/config/default.yaml",
        "--data",
        "/home/tony/APS360/config/custom_data.yaml",
        "--output_dir",
        "/home/tony/APS360/src/datasets/yolo_ucy",
        "--dry_run"
    ],
    "state": "running",
    "program": "/home/tony/APS360/src/model.py",
    "codePathLocal": null,
    "codePath": "src/model.py",
    "git": {
        "remote": "git@github.com:Tonytheiv/APS360.git",
        "commit": "39b8b7d12d4d9bd7f3a71a78d4f79aa06212fdc0"
    },
    "email": "tonytheiv@icloud.com",
    "root": "/home/tony/APS360",
    "host": "guam",
    "username": "tony",
    "executable": "/usr/bin/python3",
    "cpu_count": 8,
    "cpu_count_logical": 8,
    "cpu_freq": {
        "current": 3616.448375,
        "min": 800.0,
        "max": 4900.0
    },
    "cpu_freq_per_core": [
        {
            "current": 3600.0,
            "min": 800.0,
            "max": 4900.0
        },
        {
            "current": 3600.0,
            "min": 800.0,
            "max": 4900.0
        },
        {
            "current": 3600.0,
            "min": 800.0,
            "max": 4900.0
        },
        {
            "current": 3600.0,
            "min": 800.0,
            "max": 4900.0
        },
        {
            "current": 3600.0,
            "min": 800.0,
            "max": 4900.0
        },
        {
            "current": 3600.0,
            "min": 800.0,
            "max": 4900.0
        },
        {
            "current": 3526.921,
            "min": 800.0,
            "max": 4900.0
        },
        {
            "current": 3600.0,
            "min": 800.0,
            "max": 4900.0
        }
    ],
    "disk": {
        "/": {
            "total": 1813.9995346069336,
            "used": 1529.5307273864746
        }
    },
    "gpu": "NVIDIA GeForce RTX 2080 Ti",
    "gpu_count": 1,
    "gpu_devices": [
        {
            "name": "NVIDIA GeForce RTX 2080 Ti",
            "memory_total": 11811160064
        }
    ],
    "memory": {
        "total": 31.038715362548828
    }
}
